[
  {
    "SKU": "p02",
    "Name": "Apple Watch Series 4",
    "Price": 14400.0
  },
  {
    "SKU": "p02",
    "Name": "Apple Watch Series 4",
    "Price": 14400.0
  },
  {
    "SKU": "p02",
    "Name": "Apple Watch Series 4",
    "Price": 14400.0
  },
  {
    "SKU": "p02",
    "Name": "Apple Watch Series 4",
    "Price": 14400.0
  },
  {
    "SKU": "p02",
    "Name": "Apple Watch Series 4",
    "Price": 14400.0
  },
  {
    "SKU": "p07",
    "Name": "iPhone XR",
    "Price": 29900.0
  },
  {
    "SKU": "p07",
    "Name": "iPhone XR",
    "Price": 29900.0
  },
  {
    "SKU": "p07",
    "Name": "iPhone XR",
    "Price": 29900.0
  },
  {
    "SKU": "p07",
    "Name": "iPhone XR",
    "Price": 29900.0
  },
  {
    "SKU": "p07",
    "Name": "iPhone XR",
    "Price": 29900.0
  },
  {
    "SKU": "p07",
    "Name": "iPhone XR",
    "Price": 29900.0
  }
]